{"ai_0.课程基础知识_index.md":"E4qvzhpL","ai_0.课程基础知识_python_index.md":"BQgagwmN","ai_0.课程基础知识_python_jupyter notebook.md":"Dy2ggs-4","ai_0.课程基础知识_python_matplotlib.md":"CZ8NnG-F","ai_0.课程基础知识_python_numpy.md":"DTiEusjk","ai_0.课程基础知识_python_pandas.md":"BaUSrJny","ai_0.课程基础知识_🎲概率论.md":"B7jL-8FI","ai_0.课程基础知识_📐线性代数.md":"xTlzhDk7","ai_0.课程基础知识_🔢高数.md":"BqJylE4f","ai_1.机器学习_01.机器学习基础_index.md":"CuTUzkZo","ai_1.机器学习_02_机器学习实验方法与原则_index.md":"CYiC9wVv","ai_1.机器学习_03.决策树_index.md":"jvTYsnxp","ai_1.机器学习_03.决策树_决策树构建思路与修正.md":"Bqar-gJC","ai_1.机器学习_03.决策树_决策树里随机数的作用.md":"CFwuR1iD","ai_1.机器学习_03.决策树_单棵树——一个独立的决策树模型.md":"Ck4qnavp","ai_1.机器学习_03.决策树_叶子节点概率预测.md":"Bo3QuqbH","ai_1.机器学习_03.决策树_基于决策树的lol胜负预测.md":"lQbCMcTx","ai_1.机器学习_03.决策树_随机森林与决策树的关系.md":"B19co08j","ai_1.机器学习_04.回归分析_exp2：基于回归分析的大学综合得分预测.md":"BkrJTYZi","ai_1.机器学习_04.回归分析_index.md":"CzF4c9w_","ai_1.机器学习_04.回归分析_离群点的检测.md":"DNevtGS5","ai_1.机器学习_04.回归分析_线性回归里面的相关系数和决定系数.md":"BjH4fiok","ai_1.机器学习_05.贝叶斯学习_index.md":"DeiW-eeo","ai_1.机器学习_05.贝叶斯学习_mdl和 map.md":"DmWDRidD","ai_1.机器学习_05.贝叶斯学习_叶贝斯定理  朴素叶贝斯假设 朴素叶贝斯分类器.md":"KZjX7qSd","ai_1.机器学习_05.贝叶斯学习_极大后验假设与极大似然.md":"B5hcx2wt","ai_1.机器学习_06.基于实例的学习方法_index.md":"DAMf9-Uj","ai_1.机器学习_06.基于实例的学习方法_在无限样本下，1-nn的错误率不超过贝叶斯最优错误率的2倍的解析.md":"BAB18ZTL","ai_1.机器学习_06.基于实例的学习方法_最近邻.md":"8vQKR5cR","ai_1.机器学习_07.支持向量机（svm）_index.md":"sB3Qh35I","ai_1.机器学习_07.支持向量机（svm）_分类决策函数各个部分及其意义.md":"D5sHOMiA","ai_1.机器学习_08.无监督学习_hw5.md":"D9dhj_wt","ai_1.机器学习_08.无监督学习_index.md":"Dypjqd6D","ai_1.机器学习_09.集成学习_adaboost算法核心流程.md":"DuH_TpLk","ai_1.机器学习_09.集成学习_index.md":"BWVpxv7G","ai_1.机器学习_09.集成学习_未被选中概率的公式的解析.md":"D9u__43r","ai_1.机器学习_10.深度学习基础_index.md":"KL9C-a0v","ai_1.机器学习_11.基于群体智慧的机器学习数据集构建_index.md":"BxyADj82","ai_1.机器学习_12.机器学习算法总结_index.md":"CTHPx8Kr","ai_1.机器学习_13.毕业设计_index.md":"DpVJAj-s","ai_1.机器学习_index.md":"iJ6gMlaa","ai_2.深度学习_index.md":"D5c4aObk","ai_3.npl_index.md":"BJZCABex","ai_4.算法_index.md":"B2VhARjq","ai_index.md":"C11_Hubs","api-examples.md":"BRB-EJ9y","c___1.c语言基础_01.变量.md":"DQhdpOZi","c___1.c语言基础_02.scanf 函数的缓冲区问题、整型数据类型的补充.md":"C6sZTzy4","c___1.c语言基础_03.原码、反码、补码和类型转换.md":"Df67Qgc2","c___1.c语言基础_04.流程结构之顺序结构和选择结构.md":"BtNsej6B","c___1.c语言基础_05.流程结构之循环结构和跳转语句.md":"oZ08SRHa","c___1.c语言基础_06.函数.md":"VUad81LU","c___1.c语言基础_07.数组.md":"XzCsyFe4","c___1.c语言基础_08.字符串和指针基础.md":"BR6EeumS","c___1.c语言基础_09.指针和数组.md":"DvyLNAA1","c___1.c语言基础_10.指针和函数、动态内存分配和结构体.md":"CZZH7fPm","c___1.c语言基础_index.md":"Bxbl1GoB","c___2.c__基础课程_1.基础语法和程序结构_01.数据.md":"D23QVTFx","c___2.c__基础课程_1.基础语法和程序结构_02.进制.md":"CAhD9Mgr","c___2.c__基础课程_1.基础语法和程序结构_03.运算符和类型转换.md":"CoDsBFBv","c___2.c__基础课程_1.基础语法和程序结构_04.流程结构.md":"C6TbWJeg","c___2.c__基础课程_1.基础语法和程序结构_05.数组与字符串.md":"BQeyVQ2M","c___2.c__基础课程_1.基础语法和程序结构_06.函数基础.md":"B_r2G4X-","c___2.c__基础课程_1.基础语法和程序结构_07.函数重载和递归函数.md":"uj5MxHGl","c___2.c__基础课程_1.基础语法和程序结构_08.指针基础.md":"yVYq1KDX","c___2.c__基础课程_1.基础语法和程序结构_09.指针和函数、字符串.md":"DPlUtSfq","c___2.c__基础课程_1.基础语法和程序结构_10.动态内存分配和二级指针.md":"NlCo98p3","c___2.c__基础课程_1.基础语法和程序结构_11.结构体.md":"CIeBnAUo","c___2.c__基础课程_1.基础语法和程序结构_12.c__程序组成和编译过程.md":"McXu6Ocm","c___2.c__基础课程_1.基础语法和程序结构_index.md":"DlZQ_ycb","c___2.c__基础课程_2.面向对象编程_01.面向对象编程.md":"BxTtLAI5","c___2.c__基础课程_2.面向对象编程_02.构造函数和析构函数.md":"3TPccwa9","c___2.c__基础课程_2.面向对象编程_03.引用以及拷贝构造和拷贝赋值.md":"BpwlHApD","c___2.c__基础课程_2.面向对象编程_04.运算符重载和内联.md":"CwWW_oGa","c___2.c__基础课程_2.面向对象编程_05.类型转换和异常.md":"D6hmP8k2","c___2.c__基础课程_2.面向对象编程_06.友元和静态.md":"CYLQWWYJ","c___2.c__基础课程_2.面向对象编程_index.md":"ZB59vPTY","c___2.c__基础课程_3.高级面向对象_01.设计模式之迭代器模式.md":"DKEVx5Fh","c___2.c__基础课程_3.高级面向对象_02.单例模式.md":"BoWjmi-P","c___2.c__基础课程_3.高级面向对象_03.观察者模式.md":"W6PVEJKp","c___2.c__基础课程_3.高级面向对象_04.函数对象和lambda函数.md":"DhZTCI9d","c___2.c__基础课程_3.高级面向对象_05.右值引用和移动语义.md":"BeSdCewr","c___2.c__基础课程_3.高级面向对象_06.继承.md":"BsGY1Jr_","c___2.c__基础课程_3.高级面向对象_07.多态.md":"D-BQY5Zr","c___2.c__基础课程_3.高级面向对象_08.多继承.md":"CNNMGJ_N","c___2.c__基础课程_3.高级面向对象_09.泛型编程和模板.md":"DQM6fcMa","c___2.c__基础课程_3.高级面向对象_10.顺序容器.md":"bmwEvUVu","c___2.c__基础课程_3.高级面向对象_11.关联容器.md":"DEjP01IO","c___2.c__基础课程_3.高级面向对象_12.全局算法.md":"f75D_EN_","c___2.c__基础课程_3.高级面向对象_index.md":"lFWGfQYJ","c___2.c__基础课程_index.md":"DZdsMwlb","c___3.c__进阶课程_第1节linux基础_1.linux基础操作.md":"miKMKpzG","c___3.c__进阶课程_第1节linux基础_2.linux常用指令.md":"CGnF2dxy","c___3.c__进阶课程_第1节linux基础_3.用户管理.md":"CxUqs2sC","c___3.c__进阶课程_第1节linux基础_4.shell 脚本.md":"DFyTmTRT","c___3.c__进阶课程_第1节linux基础_5.正则表达式.md":"DogcoPBa","c___3.c__进阶课程_第1节linux基础_6.makefile工程管理文件.md":"CcOFnqDP","c___3.c__进阶课程_第1节linux基础_index.md":"ByxS8zgp","c___3.c__进阶课程_第2节数据结构与基本算法_01.链表-单链表.md":"DoHkg-NZ","c___3.c__进阶课程_第2节数据结构与基本算法_02.链表-双链表.md":"BHJvy_df","c___3.c__进阶课程_第2节数据结构与基本算法_03.链表-其他形态.md":"CoWjO2i_","c___3.c__进阶课程_第2节数据结构与基本算法_04.栈与队列-栈.md":"DIDAk99j","c___3.c__进阶课程_第2节数据结构与基本算法_05.栈与队列-队列.md":"mZr_n-Mt","c___3.c__进阶课程_第2节数据结构与基本算法_06.二叉树 - 树与二叉树.md":"DflQjzGg","c___3.c__进阶课程_第2节数据结构与基本算法_07.二叉树 - 二叉排序树.md":"PKDmGKC9","c___3.c__进阶课程_第2节数据结构与基本算法_08.二叉树 - 平衡二叉树.md":"BeiMybki","c___3.c__进阶课程_第2节数据结构与基本算法_09.二叉树 - 哈夫曼树.md":"C2TeMeNr","c___3.c__进阶课程_第2节数据结构与基本算法_10.图-图的概念.md":"JSvOzn9k","c___3.c__进阶课程_第2节数据结构与基本算法_11.图-图的存储.md":"CEcVSrFU","c___3.c__进阶课程_第2节数据结构与基本算法_12.图-图的遍历.md":"uc7dbXN-","c___3.c__进阶课程_第2节数据结构与基本算法_13.图-最短路径问题.md":"CJ56NOjk","c___3.c__进阶课程_第2节数据结构与基本算法_14.基础算法.md":"DzjiLRmc","c___3.c__进阶课程_第2节数据结构与基本算法_index.md":"CzALAD8H","c___3.c__进阶课程_第3节文件io_1.系统io.md":"CwYMU34P","c___3.c__进阶课程_第3节文件io_2. 目录操作.md":"B6fkfFfY","c___3.c__进阶课程_第3节文件io_3.标准io.md":"CdFenGD9","c___3.c__进阶课程_第3节文件io_index.md":"-W0Wms5W","c___3.c__进阶课程_第4节多线程与并发_1.进程.md":"DJSB1g_h","c___3.c__进阶课程_第4节多线程与并发_2.ipc通信.md":"qGV-QQ7W","c___3.c__进阶课程_第4节多线程与并发_3. 线程.md":"Boqg3VYG","c___3.c__进阶课程_第4节多线程与并发_4.线程池.md":"DzA-CSgm","c___3.c__进阶课程_第4节多线程与并发_index.md":"BHn65Eom","c___3.c__进阶课程_第5节网络编程_1.网络编程预备知识.md":"CHIVOmkP","c___3.c__进阶课程_第5节网络编程_2.tcp和udp及通信协议.md":"D_L_6hDa","c___3.c__进阶课程_第5节网络编程_4.广播与多播.md":"DUKk5IpZ","c___3.c__进阶课程_第5节网络编程_5.unix与多路复用.md":"CrBeL0FQ","c___3.c__进阶课程_第5节网络编程_index.md":"DpO_EvI7","c___3.c__进阶课程_第6节实战_index.md":"DpjxzD0z","c___3.c__进阶课程_第6节实战_ptp项目.md":"BjT8SY-U","c___3.c__进阶课程_第6节实战_利用线程找最大值.md":"1QV6wBMe","c___3.c__进阶课程_第6节实战_双日志系统1.0.md":"DVigSbdE","c___3.c__进阶课程_第6节实战_双日志系统2.0.md":"Bhcdv5WH","c___3.c__进阶课程_第6节实战_异常安全的动态矩阵类matrix实现.md":"C33xjtIA","c___4.c__研修阶段_index.md":"BOUm2TWy","c___4.c__研修阶段_第1节数据库_1.数据库语句一库与表.md":"T8RLIduY","c___4.c__研修阶段_第1节数据库_2.数据库语句二数据操作.md":"DOU0uRTH","c___4.c__研修阶段_第1节数据库_3.数据库语句三事务与索引.md":"CzbC2ci6","c___4.c__研修阶段_第1节数据库_4.数据库c__api接口.md":"bEWP2Yee","c___4.c__研修阶段_第1节数据库_index.md":"D6wr221q","c___4.c__研修阶段_第2节qt图形库_1.qt-安装与使用.md":"BE_zLNQO","c___4.c__研修阶段_第2节qt图形库_10.文件与目录.md":"D0ngIFRC","c___4.c__研修阶段_第2节qt图形库_11.网络与多线程.md":"CXNKou3L","c___4.c__研修阶段_第2节qt图形库_12.数据库.md":"DfLvsjJn","c___4.c__研修阶段_第2节qt图形库_2.qt-元对象系统.md":"Cl6TUbam","c___4.c__研修阶段_第2节qt图形库_3. 对象树.md":"XIcE8Btw","c___4.c__研修阶段_第2节qt图形库_4.事件系统.md":"aIKN-Qwp","c___4.c__研修阶段_第2节qt图形库_5.gui开发.md":"CJJq6Pde","c___4.c__研修阶段_第2节qt图形库_6.自定义控件.md":"D0HKDNtN","c___4.c__研修阶段_第2节qt图形库_7.布局管理.md":"CG_fzRGI","c___4.c__研修阶段_第2节qt图形库_8.项目详解.md":"DeDB8PFE","c___4.c__研修阶段_第2节qt图形库_9.绘图系统.md":"D-0gT2v-","c___4.c__研修阶段_第2节qt图形库_index.md":"BknD2gza","c___4.c__研修阶段_第3节工具使用_1.visualstudio.md":"CynjOoEF","c___4.c__研修阶段_第3节工具使用_2.git远程仓库.md":"CLZCTxFm","c___4.c__研修阶段_第3节工具使用_3.cmake.md":"BmisgYlj","c___4.c__研修阶段_第3节工具使用_4.杂项.md":"CN6j3K4F","c___4.c__研修阶段_第3节工具使用_index.md":"jj4NhS1L","c___index.md":"B0LpJJWL","index.md":"DSHC6rb1","internship_index.md":"DZOAtH66","knowledge-graph.md":"TReRdvAc","markdown-examples.md":"Cmjp0ctg","postgraduate_index.md":"OlLxGCqM","resources.md":"Cc7V0X5B","我们只是通过无数的思维模型在给世界建模.md":"B5I6au9K"}
